{
  "abstract": false,
  "anchor": "",
  "attention": [
    "These values are unique to each drivetrain and must be specifically tuned. "
  ],
  "brief": "A structure describing values specific to the drivetrain's physical state. ",
  "category": "classes",
  "const": false,
  "definition": "",
  "explicit": false,
  "fullname": "tao::DifferentialDrivetrain::Config",
  "hasAdditionalMembers": false,
  "hasDetails": true,
  "includes": "<DifferentialDrivetrain.h>",
  "inline": false,
  "kind": "struct",
  "language": "cpp",
  "location": {
    "bodyEnd": 69,
    "bodyFile": "include/taolib/DifferentialDrivetrain.h",
    "bodyStart": 37,
    "column": 1,
    "file": "include/taolib/DifferentialDrivetrain.h",
    "line": 37
  },
  "name": "tao::DifferentialDrivetrain::Config",
  "override": false,
  "parent": {
    "anchor": "",
    "brief": "A class representing a nonholonomic drivetrain using position tracking and PID motion control. ",
    "category": "classes",
    "fullname": "tao::DifferentialDrivetrain",
    "kind": "class",
    "language": "cpp",
    "name": "tao::DifferentialDrivetrain",
    "qualifiedname": "tao::DifferentialDrivetrain",
    "refid": "classtao_1_1_differential_drivetrain",
    "summary": "A class representing a nonholonomic drivetrain using position tracking and PID motion control. ",
    "title": "tao::DifferentialDrivetrain",
    "url": "classtao_1_1_differential_drivetrain.md",
    "visibility": "public"
  },
  "parentBreadcrumbs": [
    {
      "anchor": "",
      "category": "namespaces",
      "fullname": "tao",
      "kind": "namespace",
      "language": "cpp",
      "name": "tao",
      "qualifiedname": "tao",
      "refid": "namespacetao",
      "title": "tao",
      "url": "namespacetao.md",
      "visibility": "public"
    },
    {
      "anchor": "",
      "brief": "A class representing a nonholonomic drivetrain using position tracking and PID motion control. ",
      "category": "classes",
      "fullname": "tao::DifferentialDrivetrain",
      "kind": "class",
      "language": "cpp",
      "name": "tao::DifferentialDrivetrain",
      "qualifiedname": "tao::DifferentialDrivetrain",
      "refid": "classtao_1_1_differential_drivetrain",
      "summary": "A class representing a nonholonomic drivetrain using position tracking and PID motion control. ",
      "title": "tao::DifferentialDrivetrain",
      "url": "classtao_1_1_differential_drivetrain.md",
      "visibility": "public"
    }
  ],
  "publicAttributes": [
    {
      "abstract": false,
      "anchor": "#variable-drive-gains",
      "brief": "The PID tuning constants used by the drive velocity PID controller. ",
      "category": "attributes",
      "const": false,
      "definition": "PIDController::Gains tao::DifferentialDrivetrain::Config::drive_gains",
      "explicit": false,
      "fullname": "tao::DifferentialDrivetrain::Config::drive_gains",
      "hasDetails": false,
      "inline": false,
      "kind": "variable",
      "language": "cpp",
      "location": {
        "bodyFile": "include/taolib/DifferentialDrivetrain.h",
        "bodyStart": 39,
        "column": 22,
        "file": "include/taolib/DifferentialDrivetrain.h",
        "line": 39
      },
      "name": "drive_gains",
      "override": false,
      "qualifiedname": "tao::DifferentialDrivetrain::Config::drive_gains",
      "refid": "structtao_1_1_differential_drivetrain_1_1_config_1afbf97448667d9bb1edacdfe21c14a824",
      "static": false,
      "strong": false,
      "summary": "The PID tuning constants used by the drive velocity PID controller. ",
      "title": "drive_gains",
      "type": "[PIDController::Gains](structtao_1_1_p_i_d_controller_1_1_gains.md)",
      "typePlain": "PIDController::Gains",
      "url": "structtao_1_1_differential_drivetrain_1_1_config.md#variable-drive-gains",
      "visibility": "public"
    },
    {
      "abstract": false,
      "anchor": "#variable-turn-gains",
      "brief": "The PID tuning constants used by the turn velocity PID controller. ",
      "category": "attributes",
      "const": false,
      "definition": "PIDController::Gains tao::DifferentialDrivetrain::Config::turn_gains",
      "explicit": false,
      "fullname": "tao::DifferentialDrivetrain::Config::turn_gains",
      "hasDetails": false,
      "inline": false,
      "kind": "variable",
      "language": "cpp",
      "location": {
        "bodyFile": "include/taolib/DifferentialDrivetrain.h",
        "bodyStart": 42,
        "column": 22,
        "file": "include/taolib/DifferentialDrivetrain.h",
        "line": 42
      },
      "name": "turn_gains",
      "override": false,
      "qualifiedname": "tao::DifferentialDrivetrain::Config::turn_gains",
      "refid": "structtao_1_1_differential_drivetrain_1_1_config_1abe9b27159f83c6ab39284e7cd0b8b242",
      "static": false,
      "strong": false,
      "summary": "The PID tuning constants used by the turn velocity PID controller. ",
      "title": "turn_gains",
      "type": "[PIDController::Gains](structtao_1_1_p_i_d_controller_1_1_gains.md)",
      "typePlain": "PIDController::Gains",
      "url": "structtao_1_1_differential_drivetrain_1_1_config.md#variable-turn-gains",
      "visibility": "public"
    },
    {
      "abstract": false,
      "anchor": "#variable-drive-tolerance",
      "brief": "The minimum acceptable error threshold (in arbitrary distance units) for the drive PID controller to consider its movement settled. ",
      "category": "attributes",
      "const": false,
      "definition": "double tao::DifferentialDrivetrain::Config::drive_tolerance",
      "explicit": false,
      "fullname": "tao::DifferentialDrivetrain::Config::drive_tolerance",
      "hasDetails": false,
      "inline": false,
      "kind": "variable",
      "language": "cpp",
      "location": {
        "bodyFile": "include/taolib/DifferentialDrivetrain.h",
        "bodyStart": 45,
        "column": 8,
        "file": "include/taolib/DifferentialDrivetrain.h",
        "line": 45
      },
      "name": "drive_tolerance",
      "override": false,
      "qualifiedname": "tao::DifferentialDrivetrain::Config::drive_tolerance",
      "refid": "structtao_1_1_differential_drivetrain_1_1_config_1a0fc42beeee1d45bb90be7f84fb4e6d05",
      "static": false,
      "strong": false,
      "summary": "The minimum acceptable error threshold (in arbitrary distance units) for the drive PID controller to consider its movement settled. ",
      "title": "drive_tolerance",
      "type": "double",
      "typePlain": "double",
      "url": "structtao_1_1_differential_drivetrain_1_1_config.md#variable-drive-tolerance",
      "visibility": "public"
    },
    {
      "abstract": false,
      "anchor": "#variable-turn-tolerance",
      "brief": "The minimum acceptable error threshold (in degrees) for the turn PID controller to consider its movement settled. ",
      "category": "attributes",
      "const": false,
      "definition": "double tao::DifferentialDrivetrain::Config::turn_tolerance",
      "explicit": false,
      "fullname": "tao::DifferentialDrivetrain::Config::turn_tolerance",
      "hasDetails": false,
      "inline": false,
      "kind": "variable",
      "language": "cpp",
      "location": {
        "bodyFile": "include/taolib/DifferentialDrivetrain.h",
        "bodyStart": 48,
        "column": 8,
        "file": "include/taolib/DifferentialDrivetrain.h",
        "line": 48
      },
      "name": "turn_tolerance",
      "override": false,
      "qualifiedname": "tao::DifferentialDrivetrain::Config::turn_tolerance",
      "refid": "structtao_1_1_differential_drivetrain_1_1_config_1aacca7581883a4bcad241fb5291c68d70",
      "static": false,
      "strong": false,
      "summary": "The minimum acceptable error threshold (in degrees) for the turn PID controller to consider its movement settled. ",
      "title": "turn_tolerance",
      "type": "double",
      "typePlain": "double",
      "url": "structtao_1_1_differential_drivetrain_1_1_config.md#variable-turn-tolerance",
      "visibility": "public"
    },
    {
      "abstract": false,
      "anchor": "#variable-lookahead-distance",
      "brief": "The radius that the robot will use to find lookahead points when following a curve using pure pursuit. ",
      "category": "attributes",
      "const": false,
      "definition": "double tao::DifferentialDrivetrain::Config::lookahead_distance",
      "explicit": false,
      "fullname": "tao::DifferentialDrivetrain::Config::lookahead_distance",
      "hasDetails": false,
      "inline": false,
      "kind": "variable",
      "language": "cpp",
      "location": {
        "bodyFile": "include/taolib/DifferentialDrivetrain.h",
        "bodyStart": 51,
        "column": 8,
        "file": "include/taolib/DifferentialDrivetrain.h",
        "line": 51
      },
      "name": "lookahead_distance",
      "override": false,
      "qualifiedname": "tao::DifferentialDrivetrain::Config::lookahead_distance",
      "refid": "structtao_1_1_differential_drivetrain_1_1_config_1afd2634dad9336382c446deec6cff63d2",
      "static": false,
      "strong": false,
      "summary": "The radius that the robot will use to find lookahead points when following a curve using pure pursuit. ",
      "title": "lookahead_distance",
      "type": "double",
      "typePlain": "double",
      "url": "structtao_1_1_differential_drivetrain_1_1_config.md#variable-lookahead-distance",
      "visibility": "public"
    },
    {
      "abstract": false,
      "anchor": "#variable-track-width",
      "brief": "The distance between the left and right drivetrain wheels. ",
      "category": "attributes",
      "const": false,
      "definition": "double tao::DifferentialDrivetrain::Config::track_width",
      "explicit": false,
      "fullname": "tao::DifferentialDrivetrain::Config::track_width",
      "hasDetails": true,
      "inline": false,
      "kind": "variable",
      "language": "cpp",
      "location": {
        "bodyFile": "include/taolib/DifferentialDrivetrain.h",
        "bodyStart": 57,
        "column": 8,
        "file": "include/taolib/DifferentialDrivetrain.h",
        "line": 57
      },
      "name": "track_width",
      "note": [
        "If an imu is unavailable (unplugged or not provided), this number will be used for calculating the drivetrain's absolute heading. "
      ],
      "override": false,
      "qualifiedname": "tao::DifferentialDrivetrain::Config::track_width",
      "refid": "structtao_1_1_differential_drivetrain_1_1_config_1a2a32550be83876129518caf7b24c8212",
      "static": false,
      "strong": false,
      "summary": "The distance between the left and right drivetrain wheels. ",
      "title": "track_width",
      "type": "double",
      "typePlain": "double",
      "url": "structtao_1_1_differential_drivetrain_1_1_config.md#variable-track-width",
      "visibility": "public"
    },
    {
      "abstract": false,
      "anchor": "#variable-wheel-diameter",
      "attention": [
        "If using external encoders, this measurement should be the radius of the drivetrain's tracking wheels. Otherwise, these measurements should be the radius of the drivetrain's powered wheels. "
      ],
      "brief": "The radius of the drivetrain's wheels. ",
      "category": "attributes",
      "const": false,
      "definition": "double tao::DifferentialDrivetrain::Config::wheel_diameter",
      "details": "This measurement will determine the units used for movement. ",
      "explicit": false,
      "fullname": "tao::DifferentialDrivetrain::Config::wheel_diameter",
      "hasDetails": true,
      "inline": false,
      "kind": "variable",
      "language": "cpp",
      "location": {
        "bodyFile": "include/taolib/DifferentialDrivetrain.h",
        "bodyStart": 63,
        "column": 8,
        "file": "include/taolib/DifferentialDrivetrain.h",
        "line": 63
      },
      "name": "wheel_diameter",
      "override": false,
      "qualifiedname": "tao::DifferentialDrivetrain::Config::wheel_diameter",
      "refid": "structtao_1_1_differential_drivetrain_1_1_config_1acc62726ce1ebb724c684a922b26032fe",
      "static": false,
      "strong": false,
      "summary": "The radius of the drivetrain's wheels. ",
      "title": "wheel_diameter",
      "type": "double",
      "typePlain": "double",
      "url": "structtao_1_1_differential_drivetrain_1_1_config.md#variable-wheel-diameter",
      "visibility": "public"
    },
    {
      "abstract": false,
      "anchor": "#variable-gearing",
      "brief": "The external gear ratio of the robot as a quotient (INPUT TEETH / OUTPUT TEETH). ",
      "category": "attributes",
      "const": false,
      "definition": "double tao::DifferentialDrivetrain::Config::gearing",
      "explicit": false,
      "fullname": "tao::DifferentialDrivetrain::Config::gearing",
      "hasDetails": false,
      "inline": false,
      "kind": "variable",
      "language": "cpp",
      "location": {
        "bodyFile": "include/taolib/DifferentialDrivetrain.h",
        "bodyStart": 68,
        "column": 8,
        "file": "include/taolib/DifferentialDrivetrain.h",
        "line": 68
      },
      "name": "gearing",
      "override": false,
      "qualifiedname": "tao::DifferentialDrivetrain::Config::gearing",
      "refid": "structtao_1_1_differential_drivetrain_1_1_config_1a335149c7771d63d199a4a3b7de545503",
      "static": false,
      "strong": false,
      "summary": "The external gear ratio of the robot as a quotient (INPUT TEETH / OUTPUT TEETH). ",
      "title": "gearing",
      "type": "double",
      "typePlain": "double",
      "url": "structtao_1_1_differential_drivetrain_1_1_config.md#variable-gearing",
      "visibility": "public"
    }
  ],
  "qualifiedname": "tao::DifferentialDrivetrain::Config",
  "refid": "structtao_1_1_differential_drivetrain_1_1_config",
  "static": false,
  "strong": false,
  "summary": "A structure describing values specific to the drivetrain's physical state. ",
  "title": "tao::DifferentialDrivetrain::Config",
  "url": "structtao_1_1_differential_drivetrain_1_1_config.md",
  "visibility": "public"
}